ytdl_nfo/Ytdl_nfo.py
ytdl_nfo/__init__.py
ytdl_nfo/__main__.py
ytdl_nfo/configs/bilibili.yaml
ytdl_nfo/configs/vimeo.yaml
ytdl_nfo/configs/youtube.yaml
ytdl_nfo/configs/zype.yaml
ytdl_nfo/nfo.py
ytdl_nfo-0.3.0.dist-info/LICENSE
ytdl_nfo-0.3.0.dist-info/METADATA
ytdl_nfo-0.3.0.dist-info/WHEEL
ytdl_nfo-0.3.0.dist-info/entry_points.txt
ytdl_nfo-0.3.0.dist-info/RECORD
