Metadata-Version: 2.1
Name: ytdl-nfo
Version: 0.3.0
Summary: Utility to convert youtube-dl/yt-dlp json metadata to .nfo
Home-page: https://github.com/owdevel/ytdl-nfo
License: Unlicense
Author: Owen
Author-email: owdevel@gmail.com
Requires-Python: >=3.8,<4.0
Classifier: License :: OSI Approved
Classifier: Programming Language :: Python :: 3
Classifier: Programming Language :: Python :: 3.8
Classifier: Programming Language :: Python :: 3.9
Classifier: Programming Language :: Python :: 3.10
Classifier: Programming Language :: Python :: 3.11
Requires-Dist: PyYAML (>=6.0,<7.0)
Project-URL: Repository, https://github.com/owdevel/ytdl-nfo
